README.md
setup.py
CharObj/__init__.py
CharObj/__main__.py
CharObj.egg-info/PKG-INFO
CharObj.egg-info/SOURCES.txt
CharObj.egg-info/dependency_links.txt
CharObj.egg-info/requires.txt
CharObj.egg-info/top_level.txt
CharObj/_dicts/__init__.py
CharObj/_dicts/armor.json
CharObj/_dicts/general_items.json
CharObj/_dicts/tools.json
CharObj/_dicts/trade_items.json
CharObj/_dicts/weapons.json
CharObj/_objects/__init__.py
CharObj/_objects/meta.py
CharObj/_objects/_items/__init__.py
CharObj/_objects/_items/catalogues.py
CharObj/_objects/_items/item.py
CharObj/_objects/_items/_armor/__init__.py
CharObj/_objects/_items/_armor/armor.py
CharObj/_objects/_items/_clothing/__init__.py
CharObj/_objects/_items/_clothing/clothing.py
CharObj/_objects/_items/_weapon/__init__.py
CharObj/_objects/_items/_weapon/weapon.py