Metadata-Version: 2.1
Name: CharObj
Version: 0.2.1
Summary: A package for creating objects for a text-based RPG
Home-page: https://github.com/primal-coder/CharObj
Author: James Evans
Author-email: joesaysahoy@gmail.com
License: MIT
Keywords: game development
Classifier: Development Status :: 3 - Alpha
Classifier: Intended Audience :: Developers
Classifier: Topic :: Games/Entertainment :: Role-Playing
Classifier: License :: OSI Approved :: MIT License
Classifier: Programming Language :: Python :: 3.7
Requires-Python: >=3.7
Requires-Dist: pyglet
Requires-Dist: dicepy
Requires-Dist: gridengine_framework
